Metadata-Version: 1.0
Name: my-first-lib-edward-colo
Version: 0.1.0
Summary: This is my first library by Edward Kolodziejski. f    Feel free to use unless you are a muggle. Your and the only, Edward.K.
Home-page: UNKNOWN
Author: Edward Kolodziejski
Author-email: edward.kolodziejski@pm.me
License: UNKNOWN
Platform: UNKNOWN
